README.rst
setup.cfg
setup.py
hpdr/__init__.py
hpdr/api.py
hpdr/enums.py
hpdr/models.py
hpdr/parse.py
hpdr/utils.py
hpdr.egg-info/PKG-INFO
hpdr.egg-info/SOURCES.txt
hpdr.egg-info/dependency_links.txt
hpdr.egg-info/not-zip-safe
hpdr.egg-info/requires.txt
hpdr.egg-info/top_level.txt
tests/__init__.py
tests/test_all.py
tests/test_large.py
tests/test_parse.py
tests/test_steps.py